crowdstrikeclient/Crowdstrike.py
crowdstrikeclient/_CrowdstrikeDetects.py
crowdstrikeclient/_CrowdstrikeHost.py
crowdstrikeclient/_CrowdstrikeIntel.py
crowdstrikeclient/_CrowdstrikeIoC.py
crowdstrikeclient/_CrowdstrikeSensor.py
crowdstrikeclient/_CrowdstrikeUserMenagement.py
crowdstrikeclient/__init__.py
crowdstrike_client-0.0.5.dist-info/LICENSE
crowdstrike_client-0.0.5.dist-info/METADATA
crowdstrike_client-0.0.5.dist-info/WHEEL
crowdstrike_client-0.0.5.dist-info/top_level.txt
crowdstrike_client-0.0.5.dist-info/RECORD
